[{"id":"group","name":"котельная","child":[{"id":"6","name":"котел"},{"id":"7","name":"расш.бак"},{"id":"8","name":"цирк.насос"},{"id":"9","name":"группа безопасности"},{"id":"10","name":"фильтр косой 3/4"},{"id":"14","name":"фильтр косой 3/4"},{"id":"11","name":"фильтр косой 1"}],"valueId":"55555"},{"id":"group","name":"радиаторы","child":[{"id":"3","name":"ал.радиатор h500"},{"id":"120","name":"ал.радиатор h200 (2 шт.)"},{"id":"119","name":"ал.радиатор h600 (6 шт.)"},{"id":"118","name":"ст.радиатор 1х0.6"},{"id":"121","name":"ст.радиатор 1.5х0.6"},{"id":"4","name":"рад.переходник 1/2"},{"id":"5","name":"рад.переходник 3/4"},{"id":"12","name":"терморегулятор"},{"id":"13","name":"терморегулирующий кран 1/2"}],"valueId":""},{"id":"group","name":"полипропилен","child":[{"id":"group","name":"углы","child":[{"id":"15","name":"угол 20"},{"id":"16","name":"угол 20х1/2(нр)"},{"id":"17","name":"угол 20х1/2(вн)"},{"id":"18","name":"угол 20х3/4(нр)"},{"id":"19","name":"угол 20х3/4(вн)"},{"id":"20","name":"угол 25"},{"id":"21","name":"угол 25х1/2(нр)"},{"id":"22","name":"угол 25х1/2(вн)"},{"id":"23","name":"угол 25х3/4(нр)"},{"id":"24","name":"угол 25х3/4(вн)"},{"id":"25","name":"угол 32"},{"id":"26","name":"угол 32х1(нр)"},{"id":"27","name":"угол 32х1(вн)"},{"id":"28","name":"угол 32х3/4(нр)"},{"id":"29","name":"угол 32х3/4(вн)"},{"id":"30","name":"угол 40"},{"id":"31","name":"угол 50"}],"valueId":"1111123"},{"id":"group","name":"тройники","child":[{"id":"32","name":"тройник 20"},{"id":"33","name":"тройник 25"},{"id":"35","name":"тройник 32"},{"id":"38","name":"тройник 40"},{"id":"40","name":"тройник 50"},{"id":"34","name":"тройник 25х20х25"},{"id":"36","name":"тройник 32х20х25"},{"id":"37","name":"тройник 32х25х32"},{"id":"39","name":"тройник 40х32х40"},{"id":"41","name":"тройник 50х40х50"}],"valueId":""},{"id":"group","name":"переходник","child":[{"id":"42","name":"переходник 20х1/2"},{"id":"43","name":"переходник 20х1/2(вн)"},{"id":"44","name":"переходник 20х3/4(нр)"},{"id":"45","name":"переходник 20х3/4(вн)"},{"id":"46","name":"переходник 25х1/2(нр)"},{"id":"47","name":"переходник 25х1/2(вн)"},{"id":"48","name":"переходник 25х3/4(нр)"},{"id":"49","name":"переходник 25х3/4(вн)"},{"id":"50","name":"переходник 32х1(нр)"},{"id":"51","name":"переходник 32х1(вн)"},{"id":"52","name":"переходник 32х3/4(нр)"},{"id":"53","name":"переходник 32х3/4(вн)"}],"valueId":""}],"valueId":""},{"id":"group","name":"металл","child":[],"valueId":""},{"id":"group","name":"металлопластик","child":[{"id":"group","name":"углы","child":[{"id":"88","name":"уг.16x1/2(нр)"},{"id":"89","name":"уг.16x1/2(вн)"},{"id":"90","name":"уг.16x3/4(нр)"},{"id":"91","name":"уг.16x3/4(вн)"},{"id":"92","name":"уг.20x1/2(нр)"},{"id":"93","name":"уг.20x1/2(вн)"},{"id":"94","name":"уг.20x3/4(нр)"},{"id":"95","name":"уг.20x3/4(вн)"},{"id":"96","name":"уг.26x1(нр)"},{"id":"97","name":"уг.26x1(вн)"},{"id":"98","name":"уг.26x3/4(нр)"},{"id":"99","name":"уг.26x3/4(вн)"},{"id":"100","name":"уг.32x1_1/4(нр)"},{"id":"101","name":"уг.32x1_1/4(вн)"},{"id":"102","name":"уг.32x1(нр)"},{"id":"103","name":"уг.32x1(вн)"}],"valueId":""},{"id":"group","name":"тройник","child":[{"id":"75","name":"тр. 16х16х16"},{"id":"77","name":"тр.20х20х20"},{"id":"81","name":"тр.26"},{"id":"87","name":"тр.32"},{"id":"76","name":"тр.20х1/2(вн)х20"},{"id":"78","name":"тр.26х1/2(вн)х26"},{"id":"79","name":"тр.26х16х20"},{"id":"80","name":"тр.26х16х26"},{"id":"82","name":"тр.32х1(вн)х32"},{"id":"83","name":"тр.32х1/2(вн)х32"},{"id":"84","name":"тр.32х20х32"},{"id":"85","name":"тр.32х26х26"},{"id":"86","name":"тр.32х26х32"}],"valueId":""},{"id":"group","name":"переходник","child":[{"id":"54","name":"перех.16х1/2(нр)"},{"id":"55","name":"перех.16х1/2(вн)"},{"id":"56","name":"перех.16х3/4(нр)"},{"id":"57","name":"перех.16х3/4(вн)"},{"id":"58","name":"перех.20х1/2(нр)"},{"id":"59","name":"перех.20х1/2(вн)"},{"id":"60","name":"перех.20х3/4(нр)"},{"id":"61","name":"перех.20х3/4(вн)"},{"id":"62","name":"перех.26х20"},{"id":"63","name":"перех.26х1(нр)"},{"id":"64","name":"перех.26х1(вн)"},{"id":"65","name":"перех.26х3/4(нр)"},{"id":"66","name":"перех.26х3/4(вн)"},{"id":"67","name":"перех.26х16"},{"id":"68","name":"перех.32х1_1/4(нр)"},{"id":"69","name":"перех.32х1_1/4(вн)"},{"id":"70","name":"перех.32х1(нр)"},{"id":"71","name":"перех.32х1(вн)"},{"id":"72","name":"перех.32х16"},{"id":"73","name":"перех.32х20"},{"id":"74","name":"перех.32х26"}],"valueId":""}],"valueId":""},{"id":"group","name":"краны","child":[{"id":"106","name":"кран 1/2(вн-вн)"},{"id":"107","name":"кран 3/4(вн-вн)"},{"id":"108","name":"кран 1(вн-вн)"},{"id":"109","name":"кран 1/2(нр-вн)"},{"id":"110","name":"кран 3/4(нр-вн)"},{"id":"111","name":"кран 1(нр-вн)"},{"id":"112","name":"кран 1/2(нр-нр)"},{"id":"113","name":"кран 3/4(нр-нр)"},{"id":"114","name":"кран 1(нр-нр)"},{"id":"115","name":"кран 1/2(сгон-вн)"},{"id":"116","name":"кран 3/4(сгон-вн)"},{"id":"117","name":"кран 1(сгон-вн)"}],"valueId":""},{"id":"104","name":"труба 2"},{"id":"105","name":"труба 3"},{"id":"122","name":"тройник"}]